test/__init__.py
test/test_parser.py
ts_interface_parser-0.0.1.dist-info/LICENSE
ts_interface_parser-0.0.1.dist-info/METADATA
ts_interface_parser-0.0.1.dist-info/WHEEL
ts_interface_parser-0.0.1.dist-info/top_level.txt
ts_interface_parser-0.0.1.dist-info/RECORD
