Metadata-Version: 2.1
Name: ts-interface-parser
Version: 0.0.1
Summary: The typescript interface parser parses interfaces defined in typescript and outputs a JSON object describing the interfaces.
Home-page: https://github.com/highkite/ts_interface_parser
Author: Thomas Osterland
Author-email: highway.ita07@web.de
License: UNKNOWN
Platform: UNKNOWN
Classifier: Programming Language :: Python :: 3
Classifier: License :: OSI Approved :: MIT License
Classifier: Operating System :: OS Independent
Requires-Python: >=3.6
